<?xml version="1.0" encoding="UTF-8"?>
<objects serializationModel="Studio.02.02.00">
	<object class="EffectPreset" id="{f7250d07-7656-4aa2-b073-9b16a254d901}">
		<property name="name">
			<value>Effect Chain</value>
		</property>
		<relationship name="folder">
			<destination>{01d1ba8c-50a1-4310-b6b2-e4b17a7f8ba5}</destination>
		</relationship>
		<relationship name="effect">
			<destination>{5381f456-7601-452b-80d6-5b389add140a}</destination>
		</relationship>
	</object>
	<object class="EffectChain" id="{5381f456-7601-452b-80d6-5b389add140a}" />
</objects>
